manage.py
mezmorize/__init__.py
mezmorize/backends.py
mezmorize/utils.py
mezmorize-0.31.0.dist-info/licenses/LICENSE
mezmorize-0.31.0.dist-info/METADATA
mezmorize-0.31.0.dist-info/WHEEL
mezmorize-0.31.0.dist-info/entry_points.txt
mezmorize-0.31.0.dist-info/top_level.txt
mezmorize-0.31.0.dist-info/RECORD
