Metadata-Version: 2.4
Name: mezmorize
Version: 0.31.0
Summary: Adds function memoization support
Author-email: Reuben Cummings <reubano@gmail.com>
Maintainer-email: Reuben Cummings <reubano@gmail.com>
License-Expression: BSD-3-Clause
Project-URL: repository, https://github.com/reubano/mezmorize
Project-URL: download, https://github.com/reubano/mezmorize/archive/refs/heads/master.zip
Project-URL: bugtracker, https://github.com/reubano/mezmorize/issues
Keywords: memoize,memoization,Flask-Cache,cache
Classifier: Development Status :: 4 - Beta
Classifier: Natural Language :: English
Classifier: Programming Language :: Python :: 3
Classifier: Programming Language :: Python :: 3.10
Classifier: Programming Language :: Python :: 3.11
Classifier: Programming Language :: Python :: 3.12
Classifier: Programming Language :: Python :: 3.13
Classifier: Programming Language :: Python :: Implementation :: PyPy
Classifier: Environment :: Console
Classifier: Topic :: Software Development :: Libraries :: Python Modules
Classifier: Intended Audience :: Developers
Classifier: Operating System :: POSIX :: Linux
Classifier: Operating System :: MacOS :: MacOS X
Classifier: Operating System :: Microsoft :: Windows
Requires-Python: >=3.10.14
License-File: LICENSE
Requires-Dist: werkzeug<4.0.0,>=1.0.1
Requires-Dist: cachelib<1.0.0,>=0.1
Provides-Extra: dev
Requires-Dist: build[virtualenv]<2.0.0,>=1.3.0; extra == "dev"
Requires-Dist: click<9.0.0,>=8.1.7; extra == "dev"
Requires-Dist: pytest<9.0.0,>=8.4.2; extra == "dev"
Requires-Dist: pytest-cov<8.0.0,>=7.0.0; extra == "dev"
Requires-Dist: pytest-xdist[psutil]<4.0.0,>=3.8.0; extra == "dev"
Requires-Dist: pylint<4.0.0,>=2.5.0; extra == "dev"
Requires-Dist: ruff<1.0.0,>=0.13.1; extra == "dev"
Requires-Dist: tox<5.0.0,>=4.30.2; extra == "dev"
Requires-Dist: twine<4.0.0,>=3.1.1; extra == "dev"
Requires-Dist: virtualenv>=19.0.0; extra == "dev"
Provides-Extra: optional
Requires-Dist: pylibmc<2.0.0,>=1.5.2; extra == "optional"
Requires-Dist: python-binary-memcached<0.30.0,>=0.29.0; extra == "optional"
Requires-Dist: pymemcache<4.0.0,>=3.1.0; extra == "optional"
Requires-Dist: redis<4.0.0,>=3.4.1; extra == "optional"
Dynamic: license-file
